example.py
naref/__init__.py
naref/abstract.py
naref/comp.py
naref/constants.py
naref/dataset.py
naref/demo.py
naref/metrics.py
naref/topology.py
naref/classical/__init__.py
naref/classical/crc.py
naref/classical/hyper.py
naref/quantum/__init__.py
naref/quantum/hyper.py
naref/quantum/qrc.py
naref-0.0.4.dist-info/LICENSE
naref-0.0.4.dist-info/METADATA
naref-0.0.4.dist-info/WHEEL
naref-0.0.4.dist-info/top_level.txt
naref-0.0.4.dist-info/RECORD
